petab_MS/C.py
petab_MS/__init__.py
petab_MS/calculate.py
petab_MS/composite_problem.py
petab_MS/conditions.py
petab_MS/core.py
petab_MS/format_version.py
petab_MS/lint.py
petab_MS/measurements.py
petab_MS/obcetive_function.py
petab_MS/observables.py
petab_MS/parameter_mapping.py
petab_MS/parameters.py
petab_MS/petablint.py
petab_MS/problem.py
petab_MS/sampling.py
petab_MS/sbml.py
petab_MS/simulate.py
petab_MS/version.py
petab_MS/yaml.py
petab_MS/visualize/__init__.py
petab_MS/visualize/data_overview.py
petab_MS/visualize/helper_functions.py
petab_MS/visualize/plot_data_and_simulation.py
petab_MS/visualize/plotter.py
petab_MS/visualize/plotting.py
petab_MS/visualize/plotting_config.py
petab_MS-0.1.22.dist-info/LICENSE
petab_MS-0.1.22.dist-info/METADATA
petab_MS-0.1.22.dist-info/WHEEL
petab_MS-0.1.22.dist-info/entry_points.txt
petab_MS-0.1.22.dist-info/top_level.txt
petab_MS-0.1.22.dist-info/RECORD
