Metadata-Version: 2.1
Name: petab-MS
Version: 0.1.22
Summary: Parameter estimation tabular data for multi-scale models
Home-page: https://gitlab.com/fitmulticell/libpetab-python-MS
Author: The PEtab-MS developers
Author-email: EmadAlamoudi@uni-bonn.de
Requires-Python: >=3.7.1
License-File: LICENSE
Requires-Dist: numpy (>=1.15.1)
Requires-Dist: pandas (>=2.0.1)
Requires-Dist: matplotlib (>=2.2.3)
Requires-Dist: python-libsbml (>=5.17.0)
Requires-Dist: sympy
Requires-Dist: colorama
Requires-Dist: seaborn
Requires-Dist: pyyaml
Requires-Dist: jsonschema
Provides-Extra: combine
Requires-Dist: python-libcombine (>=0.2.6) ; extra == 'combine'
Provides-Extra: doc
Requires-Dist: sphinx (>=3.5.3) ; extra == 'doc'
Requires-Dist: sphinxcontrib-napoleon (>=0.7) ; extra == 'doc'
Requires-Dist: sphinx-markdown-tables (>=0.0.15) ; extra == 'doc'
Requires-Dist: sphinx-rtd-theme (>=0.5.1) ; extra == 'doc'
Requires-Dist: recommonmark (>=0.7.1) ; extra == 'doc'
Requires-Dist: nbsphinx (>=0.8.2) ; extra == 'doc'
Requires-Dist: m2r (>=0.2.1) ; extra == 'doc'
Requires-Dist: ipython (>=7.21.0) ; extra == 'doc'
Provides-Extra: reports
Requires-Dist: Jinja2 ; extra == 'reports'
